oh_sched/__init__.py
oh_sched/__main__.py
oh_sched/calendr.py
oh_sched/config.py
oh_sched/email.py
oh_sched/load.py
oh_sched/match.py
oh_sched-0.10.0.dist-info/METADATA
oh_sched-0.10.0.dist-info/WHEEL
oh_sched-0.10.0.dist-info/RECORD
