Metadata-Version: 2.3
Name: oh-sched
Version: 0.10.0
Summary: 
Author: higger
Author-email: matt.higger@gmail.com
Requires-Python: >=3.10,<4.0
Classifier: Programming Language :: Python :: 3
Classifier: Programming Language :: Python :: 3.10
Classifier: Programming Language :: Python :: 3.11
Classifier: Programming Language :: Python :: 3.12
Classifier: Programming Language :: Python :: 3.13
Requires-Dist: icalendar (>=5.0.13,<6.0.0)
Requires-Dist: levenshtein (>=0.27.1,<0.28.0)
Requires-Dist: numpy (>=2.1.1,<3.0.0)
Requires-Dist: pandas (>=2.2.2,<3.0.0)
Requires-Dist: pyyaml (>=6.0.2,<7.0.0)
Requires-Dist: scipy (>=1.14.1,<2.0.0)
Requires-Dist: tzlocal (>=5.2,<6.0)
